aworld_runtime/__init__.py
aworld_runtime/cli.py
aworld_runtime/config.py
aworld_runtime/logging_utils.py
aworld_runtime/gaia/__init__.py
aworld_runtime/gaia/api/__init__.py
aworld_runtime/gaia/api/gaia_fastapi.py
aworld_runtime/gaia/models/__init__.py
aworld_runtime/gaia/models/document.py
aworld_runtime/gaia/services/__init__.py
aworld_runtime/gaia/services/action_collection.py
aworld_runtime/gaia/services/sse_server.py
aworld_runtime/gaia/services/utils.py
aworld_runtime/gaia/services/documents/__init__.py
aworld_runtime/gaia/services/documents/csv_collection.py
aworld_runtime/gaia/services/documents/docx_collection.py
aworld_runtime/gaia/services/documents/pdf_collection.py
aworld_runtime/gaia/services/documents/pptx_collection.py
aworld_runtime/gaia/services/documents/txt_collection.py
aworld_runtime/gaia/services/documents/xlsx_collection.py
aworld_runtime/gaia/services/intelligence/__init__.py
aworld_runtime/gaia/services/intelligence/code_collection.py
aworld_runtime/gaia/services/intelligence/think_collection.py
aworld_runtime/gaia/services/media/__init__.py
aworld_runtime/gaia/services/media/audio_collection.py
aworld_runtime/gaia/services/media/image_collection.py
aworld_runtime/gaia/services/media/video_collection.py
aworld_runtime/gaia/services/tools/__init__.py
aworld_runtime/gaia/services/tools/arxiv_collection.py
aworld_runtime/gaia/services/tools/browser_collection.py
aworld_runtime/gaia/services/tools/download_collection.py
aworld_runtime/gaia/services/tools/pubchem_collection.py
aworld_runtime/gaia/services/tools/search_collection.py
aworld_runtime/gaia/services/tools/terminal_collection.py
aworld_runtime/gaia/services/tools/wayback_collection.py
aworld_runtime/gaia/services/tools/wikipedia_collection.py
aworld_runtime/gaia/services/tools/youtube_collection.py
aworld_runtime/openrouter/__init__.py
aworld_runtime/openrouter/api/__init__.py
aworld_runtime/openrouter/api/llm_fastapi.py
aworld_runtime/openrouter/models/__init__.py
aworld_runtime-0.2.0.dist-info/METADATA
aworld_runtime-0.2.0.dist-info/WHEEL
aworld_runtime-0.2.0.dist-info/entry_points.txt
aworld_runtime-0.2.0.dist-info/licenses/LICENSE
aworld_runtime-0.2.0.dist-info/RECORD
