Metadata-Version: 2.4
Name: aworld-runtime
Version: 0.2.0
Summary: Scaling Agent Training via Runtime Definitions and Parallelizations
License-File: LICENSE
Requires-Python: >=3.12
Requires-Dist: aiofiles>=24.1.0
Requires-Dist: aiohttp>=3.12.14
Requires-Dist: arxiv>=2.2.0
Requires-Dist: browser-use>=0.5.3
Requires-Dist: chardet>=5.2.0
Requires-Dist: dotenv>=0.9.9
Requires-Dist: fastapi>=0.116.0
Requires-Dist: fastmcp>=2.10.4
Requires-Dist: langchain-openai>=0.3.27
Requires-Dist: markdown>=3.8.2
Requires-Dist: mcp[cli]>=1.11.0
Requires-Dist: numpy>=2.3.1
Requires-Dist: opencv-python>=4.11.0.86
Requires-Dist: openpyxl>=3.1.5
Requires-Dist: pandas>=2.3.1
Requires-Dist: pillow>=11.3.0
Requires-Dist: pydantic>=2.11.7
Requires-Dist: pygame>=2.6.1
Requires-Dist: pytesseract>=0.3.13
Requires-Dist: python-docx>=1.2.0
Requires-Dist: python-magic>=0.4.27
Requires-Dist: python-pptx>=1.0.2
Requires-Dist: selenium>=4.34.2
Requires-Dist: typer>=0.16.0
Requires-Dist: waybackpy>=3.0.6
Requires-Dist: wikipedia>=1.4.0
Requires-Dist: youtube-transcript-api>=1.1.1
